sentry_dingding/__init__.py
sentry_dingding/forms.py
sentry_dingding/plugin.py
sentry10_dingding-0.0.2.dist-info/LICENSE
sentry10_dingding-0.0.2.dist-info/METADATA
sentry10_dingding-0.0.2.dist-info/WHEEL
sentry10_dingding-0.0.2.dist-info/entry_points.txt
sentry10_dingding-0.0.2.dist-info/top_level.txt
sentry10_dingding-0.0.2.dist-info/RECORD
