Metadata-Version: 2.1
Name: sentry10-dingding
Version: 0.0.2
Summary: A Sentry extension which send errors stats to DingDing
Home-page: https://github.com/y1024/sentry-dingding
Author: Sentrydingding2
Author-email: 1255322700@qq.com
License: MIT
Keywords: sentry dingding
Platform: UNKNOWN
Classifier: Programming Language :: Python :: 2.7
Classifier: License :: OSI Approved :: MIT License
Requires-Dist: sentry (>=9.0.0)
Requires-Dist: requests
